{"title":"김밥레코즈 ─ Bargain Bin","url":"http://gimbabrecords.com/product/list.html?cate_no=43","favicon":"http://gimbabrecords.com/product/favicon.ico","elements":[{"title":"Ludovico Einaudi / Live In Berlin (2CD) *유니버설 재즈 클래식 베스트셀러 할인","contents":"18,500원","link":"http://gimbabrecords.com/product/detail.html?product_no=24601&cate_no=43&display_group=1","retrieved":1708104903184,"image":"http://gimbabrecords.com/web/product/medium/202402/d6a451beed2dc0e7ea9eee0f4c7997a0.jpg"},{"title":"London Symphony Orchestra, Krystian Zimerman, Simon Rattle / Beethoven : Complete Piano Concertos (3CD Box Set + Bonus Blu-Ray) *2023 블랙프라이데이 할인","contents":"39,000원","link":"http://gimbabrecords.com/product/detail.html?product_no=24600&cate_no=43&display_group=1","retrieved":1708104903186,"image":"http://gimbabrecords.com/web/product/medium/202402/5cd0397176c7202eb77634c92d21a643.jpg"},{"title":"Various Artists / Chopin : Complete Edition (17CD Box Set) *2023 블랙프라이데이 할인","contents":"67,000원","link":"http://gimbabrecords.com/product/detail.html?product_no=24599&cate_no=43&display_group=1","retrieved":1708104903186,"image":"http://gimbabrecords.com/web/product/medium/202402/51ffa0a77f422504a87bcf965d5e0b83.jpg"},{"title":"Asia / The Official Live Bootlegs Volume 1 (2CD x , 10CD Box Set, Limited Edition) *2023 블랙프라이데이 할인","contents":"39,000원","link":"http://gimbabrecords.com/product/detail.html?product_no=24596&cate_no=43&display_group=1","retrieved":1708104903187,"image":"http://gimbabrecords.com/web/product/medium/202402/4cc288c6183515e077f1a1d047f2928e.jpg"},{"title":"Dire Straits & Mark Knopfler / The Best : Private Investigation (Vinyl, 2LP) *2023 블랙프라이데이 할인","contents":"45,000원","link":"http://gimbabrecords.com/product/detail.html?product_no=24595&cate_no=43&display_group=1","retrieved":1708104903188,"image":"http://gimbabrecords.com/web/product/medium/202402/a618b2af91f4182353ec8ccaf8f5eb61.jpg"},{"title":"Ali Farka Toure / Voyageur (Vinyl) *2023 블랙프라이데이 할인","contents":"34,500원","link":"http://gimbabrecords.com/product/detail.html?product_no=24593&cate_no=43&display_group=1","retrieved":1708104903189,"image":"http://gimbabrecords.com/web/product/medium/202402/aba70c9d29355e85e141277f3eccfa39.jpg"},{"title":"Asia / Live At The Budokan Tokyo 1983 - MTV Satellite Telecast To America 6 December 1983 (Vinyl, 2LP) *2023 블랙프라이데이 할인","contents":"34,500원","link":"http://gimbabrecords.com/product/detail.html?product_no=24591&cate_no=43&display_group=1","retrieved":1708104903190,"image":"http://gimbabrecords.com/web/product/medium/202402/4f4db432128c68a891205fb505d4fcff.jpg"},{"title":"The Art Of Noise / Noise In The City (Live In Tokyo, 1986) (CD) *한정수량 할인 / 2023 블랙프라이데이 할인","contents":"11,000원","link":"http://gimbabrecords.com/product/detail.html?product_no=24577&cate_no=43&display_group=1","retrieved":1707759323671,"image":"http://gimbabrecords.com/web/product/medium/202402/8eebcfa82046140e5fbbb1d0aa28a1d8.jpg"},{"title":"Sex Pistols / The Original Recordings (Vinyl, 2LP) *2023 블랙프라이데이 할인","contents":"41,500원","link":"http://gimbabrecords.com/product/detail.html?product_no=24414&cate_no=43&display_group=1","retrieved":1707327345223,"image":"http://gimbabrecords.com/web/product/medium/202402/52fd9dbfc42f95b4d93f75613dd8397d.jpg"},{"title":"Ariana Grande / Dangerous Woman (Vinyl, 2LP) *2023 블랙프라이데이 할인","contents":"38,500원","link":"http://gimbabrecords.com/product/detail.html?product_no=24405&cate_no=43&display_group=1","retrieved":1707327345224,"image":"http://gimbabrecords.com/web/product/medium/202402/1f2fb929cdb58380e4f0d92867737205.jpg"},{"title":"Metallica / 72 Seasons (CD) *2023 블랙프라이데이 할인","contents":"19,500원","link":"http://gimbabrecords.com/product/detail.html?product_no=24330&cate_no=43&display_group=1","retrieved":1707327345228,"image":"http://gimbabrecords.com/web/product/medium/202402/0a52b1622a6e4ec6021ce55a7913a91d.jpg"},{"title":"Go-Go's / Beauty And The Beat (Vinyl) *2023 블랙프라이데이 할인","contents":"29,000원","link":"http://gimbabrecords.com/product/detail.html?product_no=24328&cate_no=43&display_group=1","retrieved":1707327345231,"image":"http://gimbabrecords.com/web/product/medium/202402/526105e8bfe53a873b4de3fd7b91bf6b.jpg"}]}