{"title":"김밥레코즈 ─ CD ─ Korean","url":"http://gimbabrecords.com/product/list.html?cate_no=29","favicon":"http://gimbabrecords.com/product/favicon.ico","elements":[{"title":"오프더메뉴 (off the menu) / 정규 1집 Every Point of View (CD)","contents":"16,300원","link":"http://gimbabrecords.com/product/detail.html?product_no=23586&cate_no=29&display_group=1","retrieved":1703266522223,"image":"http://gimbabrecords.com/web/product/medium/202312/507f037856625defb40a39d46a9724b5.jpg"},{"title":"고희안 하와이 트리오 (Koheean Hawaii Trio) / Pink Island (CD)","contents":"14,900원","link":"http://gimbabrecords.com/product/detail.html?product_no=23558&cate_no=29&display_group=1","retrieved":1703007293096,"image":"http://gimbabrecords.com/web/product/medium/202312/d10ec96ff7fba58bb12fecee689089ea.jpg"},{"title":"기리보이 / 정규 10집 소설 쓰고 자빠졌네 (CD + ALBUM BOOK 120p + 내지 + 포스터 2종)","contents":"21,500원","link":"http://gimbabrecords.com/product/detail.html?product_no=23508&cate_no=29&display_group=1","retrieved":1702575313505,"image":"http://gimbabrecords.com/web/product/medium/202312/46e13ed0ca07a1a2bd45a341c987df85.jpeg"},{"title":"Tuesday Beach Club / EP Tuesday Beach Club (CD)","contents":"12,000원","link":"http://gimbabrecords.com/product/detail.html?product_no=23505&cate_no=29&display_group=1","retrieved":1702402511032,"image":"http://gimbabrecords.com/web/product/medium/202312/b35229ce021a9258d809c02b46ff2527.jpg"},{"title":"겸 GYE0M  / 남은 것들은 짙은 향기와 마지막 사랑 (CD)","contents":"18,000원","link":"http://gimbabrecords.com/product/detail.html?product_no=23443&cate_no=29&display_group=1","retrieved":1701711335148,"image":"http://gimbabrecords.com/web/product/medium/202312/92d64ab430231a0b8721b588d1a0bc0d.jpg"},{"title":"태버 (Tabber) / Madness Always Turns to Sadness (CD)","contents":"17,800원","link":"http://gimbabrecords.com/product/detail.html?product_no=23331&cate_no=29&display_group=1","retrieved":1700760910461,"image":"http://gimbabrecords.com/web/product/medium/202311/297d0d1eee939d6d8d67a953f11893bd.jpg"},{"title":"여유와 설빈 / 정규 3집 희극 (CD)","contents":"19,300원","link":"http://gimbabrecords.com/product/detail.html?product_no=23325&cate_no=29&display_group=1","retrieved":1700588255523,"image":"http://gimbabrecords.com/web/product/medium/202311/ef0b5ab887139a6b420a0bc11efa52b1.jpg"},{"title":"여유와 설빈 / 정규 2집 노래는 저 멀리 (CD)","contents":"14,900원","link":"http://gimbabrecords.com/product/detail.html?product_no=23324&cate_no=29&display_group=1","retrieved":1700588255524,"image":"http://gimbabrecords.com/web/product/medium/202311/c2aa2f87b7caed4e17a92b09690a45af.jpg"},{"title":"릴리 잇 머신 (Lilly Eat Machine) / 우리는 불연소의 여름에 갇힌 채 밤을 맞고 (CD)","contents":"12,500원","link":"http://gimbabrecords.com/product/detail.html?product_no=23323&cate_no=29&display_group=1","retrieved":1700588255526,"image":"http://gimbabrecords.com/web/product/medium/202311/f799740913a32c3cf50537041674045d.jpg"},{"title":"이민휘 / 미래의 고향 (CD, Digipak)","contents":"19,000원","link":"http://gimbabrecords.com/product/detail.html?product_no=23321&cate_no=29&display_group=1","retrieved":1700544917424,"image":"http://gimbabrecords.com/web/product/medium/202311/adb22b4c3a6a8525d876b99840139750.jpg"},{"title":"쿠인 quinn_ / 무중호흡 (EP 무중력 + 무호흡) (CD)","contents":"13,000원","link":"http://gimbabrecords.com/product/detail.html?product_no=23319&cate_no=29&display_group=1","retrieved":1700199316750,"image":"http://gimbabrecords.com/web/product/medium/202311/9be2eaa33741bbca150c6303edfe03ef.png"},{"title":"정밀아 / 정규 4집 리버사이드 (CD)","contents":"20,000원","link":"http://gimbabrecords.com/product/detail.html?product_no=23311&cate_no=29&display_group=1","retrieved":1700156098154,"image":"http://gimbabrecords.com/web/product/medium/202311/9c57817db4ff6b4e22598d8cc23978ce.jpg"}]}