{"title":"김밥레코즈 ─ CD ─ Pop/Rock","url":"http://gimbabrecords.com/product/list.html?cate_no=30","favicon":"http://gimbabrecords.com/product/favicon.ico","elements":[{"title":"Shellac / Terraform (CD, gatefold sleeve)","contents":"23,500원","link":"http://gimbabrecords.com/product/detail.html?product_no=21236&cate_no=30&display_group=1","retrieved":1675186571766,"image":"http://gimbabrecords.com/web/product/medium/202301/0dea904f1194d46e866d94ae0397c541.jpg"},{"title":"Vic Chesnutt / At the Cut (CD, gatefold sleeve)","contents":"22,500원","link":"http://gimbabrecords.com/product/detail.html?product_no=21232&cate_no=30&display_group=1","retrieved":1675186571768,"image":"http://gimbabrecords.com/web/product/medium/202301/cf1017301be8d89e5542a35595529b97.jpg"},{"title":"May Blitz / May Blitz (CD, JPN Import)","contents":"14,000원","link":"http://gimbabrecords.com/product/detail.html?product_no=21217&cate_no=30&display_group=1","retrieved":1675100153703,"image":"http://gimbabrecords.com/web/product/medium/202301/1eb68122d491803b09506a229ce4c5d5.jpg"},{"title":"Gracious / Gracious (CD, JPN Import)","contents":"14,000원","link":"http://gimbabrecords.com/product/detail.html?product_no=21216&cate_no=30&display_group=1","retrieved":1675100153705,"image":"http://gimbabrecords.com/web/product/medium/202301/13b53eee81ee2fcd83d71b6509dff4bd.jpg"},{"title":"Clear Blue Sky / Clear Blue Sky (CD, JPN Import)","contents":"14,000원","link":"http://gimbabrecords.com/product/detail.html?product_no=21215&cate_no=30&display_group=1","retrieved":1675100153707,"image":"http://gimbabrecords.com/web/product/medium/202301/6ce112fcfb07a9ca845dcb0a40a020cc.jpg"},{"title":"The World Of Oz / The World Of Oz (CD, JPN Import)","contents":"14,000원","link":"http://gimbabrecords.com/product/detail.html?product_no=21214&cate_no=30&display_group=1","retrieved":1675100153708,"image":"http://gimbabrecords.com/web/product/medium/202301/69a83e5e7795c5cb7de74d9b45017d57.jpg"},{"title":"Mark-Almond / Mark-Almond (CD, JPN Import)","contents":"14,000원","link":"http://gimbabrecords.com/product/detail.html?product_no=21213&cate_no=30&display_group=1","retrieved":1675100153710,"image":"http://gimbabrecords.com/web/product/medium/202301/c45f8f0bd26702c1d0bfbc7b4e7c398f.jpg"},{"title":"Magna Carta / Seasons (CD, JPN Import)","contents":"14,000원","link":"http://gimbabrecords.com/product/detail.html?product_no=21212&cate_no=30&display_group=1","retrieved":1675100153712,"image":"http://gimbabrecords.com/web/product/medium/202301/1f6c14da4ed2b81312223797b497cd02.jpg"},{"title":"Beggar's Opera / Act One (CD, JPN Import)","contents":"14,000원","link":"http://gimbabrecords.com/product/detail.html?product_no=21211&cate_no=30&display_group=1","retrieved":1675100153714,"image":"http://gimbabrecords.com/web/product/medium/202301/6864afc447913182c5b8a48a2d8d06fb.jpg"},{"title":"Opus Avantra / Lord Cromwell Plays Suite For Seven Vices (CD, JPN Import)","contents":"26,000원","link":"http://gimbabrecords.com/product/detail.html?product_no=21209&cate_no=30&display_group=1","retrieved":1675100153719,"image":"http://gimbabrecords.com/web/product/medium/202301/4dc7f67ae2a45fcffa7506e4e475bfd3.jpg"},{"title":"Wishbone Ash / Pilgrimage (CD, EU Import) *한정수량 할인","contents":"14,500원","link":"http://gimbabrecords.com/product/detail.html?product_no=21198&cate_no=30&display_group=1","retrieved":1675100153722,"image":"http://gimbabrecords.com/web/product/medium/202301/e132694df8a5b80997f1bb085dbab5ba.jpg"},{"title":"Amy Winehouse / The Collection (5CD Box Set) *한정수량 할인","contents":"32,500원","link":"http://gimbabrecords.com/product/detail.html?product_no=21181&cate_no=30&display_group=1","retrieved":1674840947561,"image":"http://gimbabrecords.com/web/product/medium/202301/019530cba90cdf28463f1407a36e87a0.jpg"}]}