{"title":"김밥레코즈 ─ CD ─ R&B/Soul/Funk","url":"http://gimbabrecords.com/product/list.html?cate_no=44","favicon":"http://gimbabrecords.com/product/favicon.ico","elements":[{"title":"Stevie Wonder / Song Review: A Greatest Hits Collection (CD) *한정수량 할인","contents":"15,500원","link":"http://gimbabrecords.com/product/detail.html?product_no=22701&cate_no=44&display_group=1","retrieved":1692812169509,"image":"http://gimbabrecords.com/web/product/medium/202308/3e3760dfe0b01e7e87fd5b60774e0f6a.jpg"},{"title":"Usher / 8701 (CD) *한정수량 할인","contents":"13,500원","link":"http://gimbabrecords.com/product/detail.html?product_no=22694&cate_no=44&display_group=1","retrieved":1692812169510,"image":"http://gimbabrecords.com/web/product/medium/202308/cffca819367c8651c67281769b2b8233.jpg"},{"title":"Marvin Gaye / The Very Best of Marvin Gaye (CD) *한정수량 할인","contents":"14,500원","link":"http://gimbabrecords.com/product/detail.html?product_no=22474&cate_no=44&display_group=1","retrieved":1689960981431,"image":"http://gimbabrecords.com/web/product/medium/202307/9739bd706f53f3cac5a640d26d3ea047.jpg"},{"title":"Booker T. & The MG's / Original Album Series (5CD Box Set) *한정수량 할인","contents":"26,500원","link":"http://gimbabrecords.com/product/detail.html?product_no=22473&cate_no=44&display_group=1","retrieved":1689960981434,"image":"http://gimbabrecords.com/web/product/medium/202307/65401b4cf7c277d46cf7e40b4e424106.jpg"},{"title":"Daniel Caesar / NEVER ENOUGH (CD)","contents":"25,500원","link":"http://gimbabrecords.com/product/detail.html?product_no=22472&cate_no=44&display_group=1","retrieved":1689960981436,"image":"http://gimbabrecords.com/web/product/medium/202307/f796f8119b745baa347a3513f781b339.png"},{"title":"Lauryn Hill / The Miseducation Of Lauryn Hill (CD, US Import) *한정수량 할인","contents":"14,500원","link":"http://gimbabrecords.com/product/detail.html?product_no=22439&cate_no=44&display_group=1","retrieved":1689183433096,"image":"http://gimbabrecords.com/web/product/medium/201607/4789_shop1_276299.jpg"},{"title":"Aaliyah / Age Ain'T Nothing But A Number (CD) *한정수량 할인","contents":"14,500원","link":"http://gimbabrecords.com/product/detail.html?product_no=22436&cate_no=44&display_group=1","retrieved":1689183433107,"image":"http://gimbabrecords.com/web/product/medium/202307/b6f23890f72b7d1a2e837b0a59c88212.jpg"},{"title":"Yazmin Lacey / Voice Notes (CD)","contents":"23,500원","link":"http://gimbabrecords.com/product/detail.html?product_no=22434&cate_no=44&display_group=1","retrieved":1689183433108,"image":"http://gimbabrecords.com/web/product/medium/202307/dc3751b8a51a8a38d2eb03f4db0ae50c.jpg"},{"title":"Nicola Conte / Umoja (CD)","contents":"19,500원","link":"http://gimbabrecords.com/product/detail.html?product_no=22345&cate_no=44&display_group=1","retrieved":1687930682145,"image":"http://gimbabrecords.com/web/product/medium/202306/dc9b8995fb1515597d6f65f28ae41c7b.jpg"},{"title":"Jessie Ware / What's Your Pleasure?: The Platinum Pleasure Edition (2CD)","contents":"23,500원","link":"http://gimbabrecords.com/product/detail.html?product_no=22329&cate_no=44&display_group=1","retrieved":1690392980919,"image":"http://gimbabrecords.com/web/product/medium/202306/23ab57ab0859ca71d1861da33ad5559f.jpg"},{"title":"Azymuth / Aurora (CD) *절판 시디 한정판매 (1인 1매만 구매 가능합니다.)","contents":"13,000원","link":"http://gimbabrecords.com/product/detail.html?product_no=22179&cate_no=44&display_group=1","retrieved":1685468157600,"image":"http://gimbabrecords.com/web/product/medium/202305/9ec346fe6864819e36b2d60fe08cce49.jpg"},{"title":"Azymuth / Aurora: Remixes + Originals (2CD) *절판 시디 한정판매 (1인 1매만 구매 가능합니다.)","contents":"14,000원","link":"http://gimbabrecords.com/product/detail.html?product_no=22177&cate_no=44&display_group=1","retrieved":1685468157605,"image":"http://gimbabrecords.com/web/product/medium/202305/1484f6645d8036ae4ddfbc88aa4da02e.jpg"}]}