{"title":"김밥레코즈 ─ Vinyl","url":"http://gimbabrecords.com/product/list.html?cate_no=25","favicon":"http://gimbabrecords.com/product/favicon.ico","elements":[{"title":"Aqualung / 10 Futures (Vinyl, LP + CD) *한정수량 할인","contents":"20,000원","link":"http://gimbabrecords.com/product/detail.html?product_no=20932&cate_no=25&display_group=1","retrieved":1672119321801,"image":"http://gimbabrecords.com/web/product/medium/202212/e87eb113f2ea00fd18a77620e1d9c741.jpg"},{"title":"Bobby Gillespie And Jehnny Beth / Utopian Ashes (Limited Clear VInyl) *한정 할인판매","contents":"32,500원","link":"http://gimbabrecords.com/product/detail.html?product_no=20931&cate_no=25&display_group=1","retrieved":1672119321802,"image":"http://gimbabrecords.com/web/product/medium/202212/c7a1d3b57019906d39bf1a72a97b0c53.jpg"},{"title":"Eric Clapton / Unplugged (Vinyl, 2LP) *한정수량 할인 (추가할인 - 유의사항을 확인하세요)","contents":"35,500원","link":"http://gimbabrecords.com/product/detail.html?product_no=20930&cate_no=25&display_group=1","retrieved":1672119321803,"image":"http://gimbabrecords.com/web/product/medium/202212/986f769c987b69bdf5c9febb752c4969.jpg"},{"title":"Tony Bennett & Lady Gaga / Cheek To Cheek Live! (Vinyl, 2LP) *한정수량 할인","contents":"51,500원","link":"http://gimbabrecords.com/product/detail.html?product_no=20928&cate_no=25&display_group=1","retrieved":1671816926766,"image":"http://gimbabrecords.com/web/product/medium/202212/fc332f455a99fe1d2c7cb4c826e2fd3f.jpg"},{"title":"Amos Lee / My Ideal: A Tribute to Chet Baker Sings (Vinyl + Download)","contents":"34,000원","link":"http://gimbabrecords.com/product/detail.html?product_no=20927&cate_no=25&display_group=1","retrieved":1671816926769,"image":"http://gimbabrecords.com/web/product/medium/202212/d3f5053874a75685236cbed945cbbe27.jpg"},{"title":"OST (music by James Horner) / The Amazing Spider-Man 어메이징 스파이더맨 (Translucent Blue and Red Marbled Vinyl, 2LP, Limited 10th Anniversary Edition) *한정수량 할인","contents":"37,500원","link":"http://gimbabrecords.com/product/detail.html?product_no=20926&cate_no=25&display_group=1","retrieved":1671816926771,"image":"http://gimbabrecords.com/web/product/medium/202212/7234e2dbe9c665890a24127533f2ac54.jpg"},{"title":"OST (음악 John Debney) - Elf 엘프 (Vinyl, 오리지널 스코어를 담은 Picture Disc)","contents":"37,500원","link":"http://gimbabrecords.com/product/detail.html?product_no=20915&cate_no=25&display_group=1","retrieved":1671730504583,"image":"http://gimbabrecords.com/web/product/medium/202212/9d4501a789a1798f2b298d76fd1137b1.jpg"},{"title":"산울림 / 6집 조금만 기다려요 (180g Black Vinyl, 2,500장 넘버링 한정반) *예약상품 (23년 2월 16일 발매)","contents":"46,800원","link":"http://gimbabrecords.com/product/detail.html?product_no=20911&cate_no=25&display_group=1","retrieved":1671730504586,"image":"http://gimbabrecords.com/web/product/medium/202212/c5f017de78ce01a0123351b88d5c54b2.jpg"},{"title":"산울림 / 5집 한낮의 모래시계 (180g Black Vinyl, 2,500장 넘버링 한정반) *예약상품 (23년 2월 16일 발매)","contents":"46,800원","link":"http://gimbabrecords.com/product/detail.html?product_no=20910&cate_no=25&display_group=1","retrieved":1671730504588,"image":"http://gimbabrecords.com/web/product/medium/202212/fe1889ff134ba81455ef2a81f3d34384.jpg"},{"title":"산울림 / 4집 특급열차 (180g Black Vinyl, 2,500장 넘버링 한정반) *예약상품 (23년 2월 16일 발매)","contents":"46,800원","link":"http://gimbabrecords.com/product/detail.html?product_no=20909&cate_no=25&display_group=1","retrieved":1671730504592,"image":"http://gimbabrecords.com/web/product/medium/202212/b7a4d7c78817f16e832307876a63e5f3.jpg"},{"title":"Nekosen 猫戦 / Mitsu Getsu Ki Kou 蜜・月・紀・行 (Vinyl, Limited Edition)","contents":"45,500원","link":"http://gimbabrecords.com/product/detail.html?product_no=20908&cate_no=25&display_group=1","retrieved":1671730504594,"image":"http://gimbabrecords.com/web/product/medium/202212/62bbff1dd3c870f54c1a73ffd5ebbdde.jpg"},{"title":"Tomoko Aran / 浮遊空間 (Fuyü-Kükan) (Vinyl, 2022 Pressing - Limited Clear Pink Vinyl)","contents":"49,500원","link":"http://gimbabrecords.com/product/detail.html?product_no=20907&cate_no=25&display_group=1","retrieved":1671730504598,"image":"http://gimbabrecords.com/web/product/medium/201903/70ca136848dfda22bf23cf13ea168975.jpg"}]}