{"title":"김밥레코즈 ─ Vinyl","url":"http://gimbabrecords.com/product/list.html?cate_no=25","favicon":"http://gimbabrecords.com/product/favicon.ico","elements":[{"title":"The Coral / Coral Island (Black Vinyl, 2LP)","contents":"36,500원","link":"http://gimbabrecords.com/product/detail.html?product_no=18672&cate_no=25&display_group=1","retrieved":1650001208161,"image":"http://gimbabrecords.com/web/product/medium/202204/c15352f9fa5a06336e8beb06b7ee71f2.jpg"},{"title":"The Coral / Coral Island (Limited Lime Green Color, 2LP)","contents":"43,500원","link":"http://gimbabrecords.com/product/detail.html?product_no=18671&cate_no=25&display_group=1","retrieved":1650001208172,"image":"http://gimbabrecords.com/web/product/medium/202204/8e414077419ef77ee5d7fcdeef12367e.jpg"},{"title":"Tahiti 80 / Here With You (Vinyl) *추가 할인상품 (쟈켓 옅은 주름)","contents":"31,000원","link":"http://gimbabrecords.com/product/detail.html?product_no=18670&cate_no=25&display_group=1","retrieved":1650001208173,"image":"http://gimbabrecords.com/web/product/medium/202204/804be4189b4ed63d0a1c0c9fa3fb8fb4.jpg"},{"title":"Tahiti 80 / Here With You (Vinyl) *할인상품","contents":"32,500원","link":"http://gimbabrecords.com/product/detail.html?product_no=18668&cate_no=25&display_group=1","retrieved":1650001208179,"image":"http://gimbabrecords.com/web/product/medium/202204/731a23c3f9b3120125e77f7c684a08f0.jpg"},{"title":"Holybrune / JoyRide (12\" Vinyl, EP) *1인 1매만 구매 가능","contents":"25,500원","link":"http://gimbabrecords.com/product/detail.html?product_no=18667&cate_no=25&display_group=1","retrieved":1649958103658,"image":"http://gimbabrecords.com/web/product/medium/202204/e3e55ffff355ac7104f916e9f03d118d.jpg"},{"title":"Tahiti 80 / Puzzle (Vinyl, 2022 Pressing) *추가 할인상품 (쟈켓에 옅은 주름이 있습니다.)","contents":"31,000원","link":"http://gimbabrecords.com/product/detail.html?product_no=18666&cate_no=25&display_group=1","retrieved":1649958103681,"image":"http://gimbabrecords.com/web/product/medium/202204/f53696edf1259c95ae7a92e0aaaef14b.jpg"},{"title":"Tahiti 90 / Puzzle (Vinyl, 2022 Pressing) *할인상품","contents":"32,500원","link":"http://gimbabrecords.com/product/detail.html?product_no=18665&cate_no=25&display_group=1","retrieved":1649958103684,"image":"http://gimbabrecords.com/web/product/medium/202204/a4b03d5ce0e87f642199c20f65a4300d.jpg"},{"title":"Foster the People / Torches X (2LP Orange Vinyl, 10th Anniversary Deluxe Edition)","contents":"54,300원","link":"http://gimbabrecords.com/product/detail.html?product_no=18659&cate_no=25&display_group=1","retrieved":1649871708602,"image":"http://gimbabrecords.com/web/product/medium/202204/fa24735943b0d27622de6a2a4abbd1af.jpg"},{"title":"Peter Doherty & Frederic Lo / The Fantasy Life of Poetry & Crime (Limited White Vinyl)","contents":"38,000원","link":"http://gimbabrecords.com/product/detail.html?product_no=18658&cate_no=25&display_group=1","retrieved":1649871708625,"image":"http://gimbabrecords.com/web/product/medium/202204/67d5a114bc39c9db44a4c04d6ae40ad9.jpg"},{"title":"Peter Doherty & Frederic Lo / The Fantasy Life of Poetry & Crime (Limited Red Vinyl)","contents":"38,000원","link":"http://gimbabrecords.com/product/detail.html?product_no=18657&cate_no=25&display_group=1","retrieved":1649871708631,"image":"http://gimbabrecords.com/web/product/medium/202204/82ff2d127d0204135c9991a166b8e2a8.jpg"},{"title":"Sylvan Esso / Free Love (Sky Blue Colored Vinyl)","contents":"37,500원","link":"http://gimbabrecords.com/product/detail.html?product_no=18656&cate_no=25&display_group=1","retrieved":1649871708633,"image":"http://gimbabrecords.com/web/product/medium/202204/1b55800fe4efb97ade657e8b4a140b82.jpg"},{"title":"Charli XCX / Crash (Red Opaque & Black Marbled Vinyl) *할인상품","contents":"35,000원","link":"http://gimbabrecords.com/product/detail.html?product_no=18655&cate_no=25&display_group=1","retrieved":1649871708639,"image":"http://gimbabrecords.com/web/product/medium/202204/1e8c735884c4581682df3026aa1acdab.png"}]}